gtwtools/__init__.py
gtwtools/classes.py
gtwtools/fmt_gtw.py
gtwtools/generate_gtw.py
gtwtools/interpolate.py
gtwtools/math.py
gtwtools/params_config.py
gtwtools/read_gtw.py
gtwtools/read_ipd.py
gtwtools-0.1.1.dist-info/LICENSE
gtwtools-0.1.1.dist-info/METADATA
gtwtools-0.1.1.dist-info/WHEEL
gtwtools-0.1.1.dist-info/top_level.txt
gtwtools-0.1.1.dist-info/RECORD
