Metadata-Version: 2.1
Name: gtwtools
Version: 0.1.1
Summary: A package to processes IPD files to extract observation times and star/satellite data, aligns the star data with a simplified star catalog, calculates the orientation of the camera, and writes the results into GTW-formatted files.
Home-page: https://github.com/lcx366/GTWTOOLS
Author: Chunxiao Li
Author-email: lcx366@126.com
License: MIT
Keywords: IPD,GTW
Classifier: Development Status :: 4 - Beta
Classifier: Intended Audience :: Education
Classifier: Intended Audience :: Science/Research
Classifier: Programming Language :: Python :: 3.10
Classifier: Programming Language :: Python :: 3.11
Classifier: Programming Language :: Python :: 3.12
Classifier: License :: OSI Approved :: MIT License
Requires-Python: >=3.10
License-File: LICENSE
Requires-Dist: scipy
Requires-Dist: numpy
Requires-Dist: pandas
Requires-Dist: astropy
Requires-Dist: starmatch
Requires-Dist: watchdog
